src/MCMC2ndGenTDI/__init__.py
src/MCMC2ndGenTDI/data/.gitattributes
src/MCMC2ndGenTDI/data/LISA_Instrument_ESA_orbits_tcb_orbits_4_Hz_3600_sec.dat
src/MCMC2ndGenTDI/data/LISA_Instrument_Keplerian_orbits_ppr_orbits_4_Hz_3600_sec.dat
src/MCMC2ndGenTDI/data/__init__.py
src/MCMC2ndGenTDI/data/elements_from_Cartesian_4_Hz_3600_sec.dat
src/MCMC2ndGenTDI/data/samples_Keplerian_chain_omega_emcee_backend_testing_small_ball.h5
src/MCMC2ndGenTDI/data/samples_Keplerian_chain_omega_emcee_testing_small_ball.dat
src/MCMC2ndGenTDI/examples/__init__.py
src/MCMC2ndGenTDI/run_mcmc_TDI.py
src/MCMC2ndGenTDI/settings.py
src/MCMC2ndGenTDI/utils/TDI_functions.py
src/MCMC2ndGenTDI/utils/__init__.py
src/MCMC2ndGenTDI/utils/delay_time_dependence.py
src/MCMC2ndGenTDI/utils/delay_time_dependence_Keplerian.py
src/MCMC2ndGenTDI/utils/filter_functions.py
src/MCMC2ndGenTDI/utils/mcmc_functions.py
src/MCMC2ndGenTDI/utils/mcmc_functions_Keplerian.py
mcmc2ndgentdi/.DS_Store
mcmc2ndgentdi/__init__.py
mcmc2ndgentdi/data/.gitattributes
mcmc2ndgentdi/data/LISA_Instrument_ESA_orbits_tcb_orbits_4_Hz_3600_sec.dat
mcmc2ndgentdi/data/LISA_Instrument_Keplerian_orbits_ppr_orbits_4_Hz_3600_sec.dat
mcmc2ndgentdi/data/__init__.py
mcmc2ndgentdi/data/elements_from_Cartesian_4_Hz_3600_sec.dat
mcmc2ndgentdi/data/samples_Keplerian_chain_omega_emcee_backend_testing_small_ball.h5
mcmc2ndgentdi/data/samples_Keplerian_chain_omega_emcee_testing_small_ball.dat
mcmc2ndgentdi/examples/.ipynb_checkpoints/elements_from_Cartesian-checkpoint.ipynb
mcmc2ndgentdi/examples/.ipynb_checkpoints/example_mcmc_run-checkpoint.ipynb
mcmc2ndgentdi/examples/.ipynb_checkpoints/generate_data-ESA-checkpoint.ipynb
mcmc2ndgentdi/examples/.ipynb_checkpoints/generate_data_Keplerian-checkpoint.ipynb
mcmc2ndgentdi/examples/__init__.py
mcmc2ndgentdi/examples/elements_from_Cartesian.ipynb
mcmc2ndgentdi/examples/example_mcmc_run.ipynb
mcmc2ndgentdi/examples/generate_data-ESA.ipynb
mcmc2ndgentdi/examples/generate_data_Keplerian.ipynb
mcmc2ndgentdi-1.0.10.dist-info/LICENSE
mcmc2ndgentdi-1.0.10.dist-info/METADATA
mcmc2ndgentdi-1.0.10.dist-info/WHEEL
mcmc2ndgentdi-1.0.10.dist-info/RECORD
