Metadata-Version: 2.1
Name: mcmc2ndgentdi
Version: 1.0.10
Summary: An MCMC sampler for the time-varying LISA spacecraft separations used in TDI.
Home-page: https://github.com/JessicaPage/MCMC2ndGenTDI
License: MIT
Author: Jessica Page
Author-email: jp0089@uah.edu
Requires-Python: >=3.9,<3.13
Classifier: License :: OSI Approved :: MIT License
Classifier: Programming Language :: Python :: 3
Classifier: Programming Language :: Python :: 3.9
Classifier: Programming Language :: Python :: 3.10
Classifier: Programming Language :: Python :: 3.11
Requires-Dist: emcee (>=3.1.4,<4.0.0)
Requires-Dist: h5py (>=3.9.0,<4.0.0)
Requires-Dist: lisaconstants (>=1.3.4,<2.0.0)
Requires-Dist: numpy (>=1.18,<1.24)
Requires-Dist: scipy (>=1.11.1,<2.0.0)
Requires-Dist: tqdm (>=4.65.0,<5.0.0)
Requires-Dist: zeus (>=0.1.1,<0.2.0)
Project-URL: Repository, https://github.com/JessicaPage/MCMC2ndGenTDI
